pontoon/__init__.py
pontoon/command.py
pontoon/configure.py
pontoon/exceptions.py
pontoon/log.py
pontoon/meta.py
pontoon/mocking.py
pontoon/ui.py
pontoon/cmd/__init__.py
pontoon/cmd/pontoon.py
pontoon/cmd/pontoon_configure.py
pontoon/cmd/pontoon_droplet.py
pontoon/cmd/pontoon_event.py
pontoon/cmd/pontoon_image.py
pontoon/cmd/pontoon_region.py
pontoon/cmd/pontoon_size.py
pontoon/cmd/pontoon_snapshot.py
pontoon/cmd/pontoon_sshkey.py
pontoon/lib/Account.py
pontoon/lib/Action.py
pontoon/lib/Domain.py
pontoon/lib/Droplet.py
pontoon/lib/FloatingIP.py
pontoon/lib/Image.py
pontoon/lib/Kernel.py
pontoon/lib/LICENSE.txt
pontoon/lib/Manager.py
pontoon/lib/Metadata.py
pontoon/lib/Record.py
pontoon/lib/Region.py
pontoon/lib/SSHKey.py
pontoon/lib/Size.py
pontoon/lib/__init__.py
pontoon/lib/baseapi.py
pontoon/lib/data/account/account.json
pontoon/lib/data/actions/create_completed.json
pontoon/lib/data/actions/ipv6_completed.json
pontoon/lib/data/actions/multi.json
pontoon/lib/data/domains/all.json
pontoon/lib/data/domains/create.json
pontoon/lib/data/domains/create_record.json
pontoon/lib/data/domains/records.json
pontoon/lib/data/domains/single.json
pontoon/lib/data/droplet_actions/change_kernel.json
pontoon/lib/data/droplet_actions/create.json
pontoon/lib/data/droplet_actions/disable_backups.json
pontoon/lib/data/droplet_actions/enable_ipv6.json
pontoon/lib/data/droplet_actions/enable_private_networking.json
pontoon/lib/data/droplet_actions/password_reset.json
pontoon/lib/data/droplet_actions/power_cycle.json
pontoon/lib/data/droplet_actions/power_off.json
pontoon/lib/data/droplet_actions/power_on.json
pontoon/lib/data/droplet_actions/reboot.json
pontoon/lib/data/droplet_actions/rebuild.json
pontoon/lib/data/droplet_actions/rename.json
pontoon/lib/data/droplet_actions/resize.json
pontoon/lib/data/droplet_actions/restore.json
pontoon/lib/data/droplet_actions/shutdown.json
pontoon/lib/data/droplet_actions/snapshot.json
pontoon-0.2.4.dist-info/DESCRIPTION.rst
pontoon-0.2.4.dist-info/METADATA
pontoon-0.2.4.dist-info/RECORD
pontoon-0.2.4.dist-info/WHEEL
pontoon-0.2.4.dist-info/entry_points.txt
pontoon-0.2.4.dist-info/metadata.json
pontoon-0.2.4.dist-info/top_level.txt
