Metadata-Version: 2.0
Name: pontoon
Version: 0.2.4
Summary: A Python CLI for Digital Ocean
Home-page: https://github.com/duggan/pontoon
Author: Ross Duggan
Author-email: ross@duggan.ie
License: The MIT License (MIT)
Requires-Dist: PyYAML (>=3.11)
Requires-Dist: docopt (>=0.6.2)
Requires-Dist: requests (>=2.9.1)
Requires-Dist: responses (>=0.5.1)
